README.rst
setup.py
src/fc_meshtools/__init__.py
src/fc_meshtools/benchs.py
src/fc_meshtools/demos.py
src/fc_meshtools/orthotope.py
src/fc_meshtools/simplicial.py
src/fc_meshtools/simplicial_dev.py
src/fc_meshtools/sys.py
src/fc_meshtools/utils.py
src/fc_meshtools.egg-info/PKG-INFO
src/fc_meshtools.egg-info/SOURCES.txt
src/fc_meshtools.egg-info/dependency_links.txt
src/fc_meshtools.egg-info/requires.txt
src/fc_meshtools.egg-info/top_level.txt
src/fc_meshtools/data/mesh0orth1order2D.npz
src/fc_meshtools/data/mesh0orth1order2D_small.npz
src/fc_meshtools/data/mesh0orth1order3D.npz
src/fc_meshtools/data/mesh0orth1order3D_small.npz
src/fc_meshtools/data/mesh0orth1order3Ds.npz
src/fc_meshtools/data/mesh0orth1order3Ds_small.npz
src/fc_meshtools/data/mesh0orth2order2D.npz
src/fc_meshtools/data/mesh0orth2order2D_small.npz
src/fc_meshtools/data/mesh0orth2order3D.npz
src/fc_meshtools/data/mesh0orth2order3D_small.npz
src/fc_meshtools/data/mesh0orth2order3Ds.npz
src/fc_meshtools/data/mesh0orth2order3Ds_small.npz
src/fc_meshtools/data/mesh0orth3order2D.npz
src/fc_meshtools/data/mesh0orth3order2D_small.npz
src/fc_meshtools/data/mesh0orth3order3D.npz
src/fc_meshtools/data/mesh0orth3order3D_small.npz
src/fc_meshtools/data/mesh0orth3order3Ds.npz
src/fc_meshtools/data/mesh0orth3order3Ds_small.npz
src/fc_meshtools/data/mesh0orth4order2D.npz
src/fc_meshtools/data/mesh0orth4order2D_small.npz
src/fc_meshtools/data/mesh0orth4order3D.npz
src/fc_meshtools/data/mesh0orth4order3D_small.npz
src/fc_meshtools/data/mesh0orth4order3Ds.npz
src/fc_meshtools/data/mesh0orth4order3Ds_small.npz
src/fc_meshtools/data/mesh0simp1order2D.npz
src/fc_meshtools/data/mesh0simp1order2D_small.npz
src/fc_meshtools/data/mesh0simp1order3D.npz
src/fc_meshtools/data/mesh0simp1order3D_small.npz
src/fc_meshtools/data/mesh0simp1order3Ds.npz
src/fc_meshtools/data/mesh0simp1order3Ds_small.npz
src/fc_meshtools/data/mesh0simp2order2D.npz
src/fc_meshtools/data/mesh0simp2order2D_small.npz
src/fc_meshtools/data/mesh0simp2order3D.npz
src/fc_meshtools/data/mesh0simp2order3D_small.npz
src/fc_meshtools/data/mesh0simp2order3Ds.npz
src/fc_meshtools/data/mesh0simp2order3Ds_small.npz
src/fc_meshtools/data/mesh0simp3order2D.npz
