Metadata-Version: 2.1
Name: fc-meshtools
Version: 0.2.1
Summary: The fc_meshtools package contains some simplicial meshes given by their vertices array and connectivity array
Home-page: http://www.math.univ-paris13.fr/~cuvelier/software
Author: Francois Cuvelier
Author-email: cuvelier@math.univ-paris13.fr
License: BSD
Platform: Linux
Platform: Mac OS-X
Platform: Windows
Classifier: Topic :: Scientific/Engineering
